<?xml version="1.0"?>
<?xml-stylesheet href="slides.css" type="text/css"?>
<?xml-stylesheet href="test3.css" type="text/css"?>
<!DOCTYPE Slide>

<Slide xmlns:html="http://www.w3.org/TR/REC-html40">

  <html:img src="nscp.gif" width="40" height="40" id="logo" />

  <SlideBody>
    <Heading>
      XML in Gecko
    </Heading>
    <SubHeading>
      Gecko Architecture: HTML
    </SubHeading>

    <Diagram>
    <html:img src="htmlcss.gif" />
    </Diagram>

  </SlideBody>
  
  <Bar>
    <Button xml:link="simple" href="slide12.xml">Prev</Button>
    <Button xml:link="simple" href="slide14.xml">Next</Button>
  </Bar>

</Slide>
